{
  "periodId": "m3-p10",
  "dayType": "instruction",
  "sourceLesson": "3-4",
  "classObjectiveCode": "3g",
  "classObjective": "Estimate and interpret the x- and y-intercepts of a function from its graph and describe where the function is positive and negative.",
  "workedExamples": [
    "3-4, Example 1 — Estimate Intercepts from a Graph",
    "3-4, Example 2 — Interpret Intercepts in Context",
    "3-4, Example 3 — Find and Interpret Intercepts from a Table"
  ],
  "warmUp": "What do x-intercepts and y-intercepts represent on a graph?",
  "conceptDevelopment": "Mini-lesson: intercept estimation from graphs; positive/negative intervals; contextual interpretation of zeros",
  "guidedPractice": "Teacher-led practice estimating intercepts from graphs and interpreting them in context",
  "independentPractice": "Practice problems finding and interpreting intercepts from graphs and tables; describing positive/negative intervals",
  "assessment": "Exit ticket: given a graph, identify the intercepts and describe what they mean in the context of the problem",
  "capReflection": "Why is it important to understand intercepts in context rather than just finding their numerical values?"
}